opexcore/__init__.py
opexcore/core/__init__.py
opexcore/core/request.py
opexcore/guard/__init__.py
opexcore/guard/manager.py
opexcore/guard/types/__init__.py
opexcore/guard/types/admin.py
opexcore/guard/types/node.py
opexcore/guard/types/service.py
opexcore/guard/types/stats.py
opexcore/guard/types/subscription.py
opexcore/marzban/__init__.py
opexcore/marzban/manager.py
opexcore/marzban/types/__init__.py
opexcore/marzban/types/admin.py
opexcore/marzban/types/core.py
opexcore/marzban/types/node.py
opexcore/marzban/types/subscription.py
opexcore/marzban/types/system.py
opexcore/marzban/types/user.py
opexcore/marzban/types/user_template.py
opexcore/marzneshin/__init__.py
opexcore/marzneshin/manager.py
opexcore/marzneshin/types/__init__.py
opexcore/marzneshin/types/admin.py
opexcore/marzneshin/types/inbound.py
opexcore/marzneshin/types/node.py
opexcore/marzneshin/types/service.py
opexcore/marzneshin/types/subscription.py
opexcore/marzneshin/types/system.py
opexcore/marzneshin/types/user.py
opexcore/ovpanel/__init__.py
opexcore/ovpanel/manager.py
opexcore/ovpanel/types/__init__.py
opexcore/ovpanel/types/admin.py
opexcore/ovpanel/types/node.py
opexcore/ovpanel/types/system.py
opexcore/ovpanel/types/user.py
opexcore/pasarguard/__init__.py
opexcore/pasarguard/manager.py
opexcore/pasarguard/types/__init__.py
opexcore/pasarguard/types/admin.py
opexcore/pasarguard/types/core.py
opexcore/pasarguard/types/group.py
opexcore/pasarguard/types/host.py
opexcore/pasarguard/types/node.py
opexcore/pasarguard/types/system.py
opexcore/pasarguard/types/user.py
opexcore/pasarguard/types/user_template.py
opexcore/remnawave/__init__.py
opexcore/remnawave/manager.py
opexcore/remnawave/types/__init__.py
opexcore/remnawave/types/admin.py
opexcore/remnawave/types/host.py
opexcore/remnawave/types/node.py
opexcore/remnawave/types/subscription.py
opexcore/remnawave/types/system.py
opexcore/remnawave/types/user.py
opexcore/rustneshin/__init__.py
opexcore/rustneshin/manager.py
opexcore-0.5.1.dist-info/licenses/LICENSE
opexcore-0.5.1.dist-info/METADATA
opexcore-0.5.1.dist-info/WHEEL
opexcore-0.5.1.dist-info/top_level.txt
opexcore-0.5.1.dist-info/RECORD
