Metadata-Version: 2.4
Name: opexcore
Version: 0.5.1
Summary: A unified Python SDK for managing multiple VPN panel APIs including Marzban, Marzneshin, Guard, and PasarGuard
Requires-Python: >=3.11
License-File: LICENSE
Requires-Dist: aiohttp>=3.13.2
Requires-Dist: pydantic>=2.12.4
Dynamic: license-file
